{
  "legislative_session": "2025",
  "identifier": "SCR 4",
  "title": "Amending Joint Rules of Senate and House of Delegates",
  "from_organization": "~{\"classification\": \"upper\"}",
  "classification": [
    "concurrent resolution"
  ],
  "subject": [],
  "abstracts": [],
  "other_titles": [],
  "other_identifiers": [],
  "actions": [
    {
      "description": "Filed for introduction",
      "date": "2025-02-12",
      "organization_id": "~{\"classification\": \"upper\"}",
      "classification": [
        "filing"
      ],
      "related_entities": [],
      "_processing": {
        "log_file_created": "2025-10-25T03:51:36Z"
      }
    },
    {
      "description": "Introduced in Senate",
      "date": "2025-02-12",
      "organization_id": "~{\"classification\": \"upper\"}",
      "classification": [
        "introduction"
      ],
      "related_entities": [],
      "_processing": {
        "log_file_created": "2025-10-25T03:51:36Z"
      }
    },
    {
      "description": "Immediate consideration",
      "date": "2025-02-12",
      "organization_id": "~{\"classification\": \"upper\"}",
      "classification": [],
      "related_entities": [],
      "_processing": {
        "log_file_created": "2025-10-25T03:51:36Z"
      }
    },
    {
      "description": "Committee reference dispensed",
      "date": "2025-02-12",
      "organization_id": "~{\"classification\": \"upper\"}",
      "classification": [],
      "related_entities": [],
      "_processing": {
        "log_file_created": "2025-10-25T03:51:36Z"
      }
    },
    {
      "description": "Adopted by Senate (Voice vote)",
      "date": "2025-02-12",
      "organization_id": "~{\"classification\": \"upper\"}",
      "classification": [
        "passage"
      ],
      "related_entities": [],
      "_processing": {
        "log_file_created": "2025-10-25T03:51:36Z"
      }
    },
    {
      "description": "Ordered to House",
      "date": "2025-02-12",
      "organization_id": "~{\"classification\": \"upper\"}",
      "classification": [],
      "related_entities": [],
      "_processing": {
        "log_file_created": "2025-10-25T03:51:36Z"
      }
    },
    {
      "description": "House received Senate message",
      "date": "2025-02-12",
      "organization_id": "~{\"classification\": \"lower\"}",
      "classification": [],
      "related_entities": [],
      "_processing": {
        "log_file_created": "2025-10-25T03:51:36Z"
      }
    },
    {
      "description": "Introduced in House",
      "date": "2025-02-12",
      "organization_id": "~{\"classification\": \"lower\"}",
      "classification": [
        "introduction"
      ],
      "related_entities": [],
      "_processing": {
        "log_file_created": "2025-10-25T03:51:36Z"
      }
    },
    {
      "description": "Immediate consideration",
      "date": "2025-02-12",
      "organization_id": "~{\"classification\": \"lower\"}",
      "classification": [],
      "related_entities": [],
      "_processing": {
        "log_file_created": "2025-10-25T03:51:36Z"
      }
    },
    {
      "description": "Reference dispensed",
      "date": "2025-02-12",
      "organization_id": "~{\"classification\": \"lower\"}",
      "classification": [],
      "related_entities": [],
      "_processing": {
        "log_file_created": "2025-10-25T03:51:36Z"
      }
    },
    {
      "description": "Adopted by House (Voice vote)",
      "date": "2025-02-12",
      "organization_id": "~{\"classification\": \"lower\"}",
      "classification": [
        "passage"
      ],
      "related_entities": [],
      "_processing": {
        "log_file_created": "2025-10-25T03:51:36Z"
      }
    },
    {
      "description": "Completed legislative action",
      "date": "2025-02-12",
      "organization_id": "~{\"classification\": \"lower\"}",
      "classification": [],
      "related_entities": [],
      "_processing": {
        "log_file_created": "2025-10-25T03:51:36Z"
      }
    },
    {
      "description": "Communicated to Senate",
      "date": "2025-02-12",
      "organization_id": "~{\"classification\": \"lower\"}",
      "classification": [],
      "related_entities": [],
      "_processing": {
        "log_file_created": "2025-10-25T03:51:36Z"
      }
    },
    {
      "description": "House Message received",
      "date": "2025-02-12",
      "organization_id": "~{\"classification\": \"upper\"}",
      "classification": [],
      "related_entities": [],
      "_processing": {
        "log_file_created": "2025-10-25T03:51:36Z"
      }
    }
  ],
  "sponsorships": [
    {
      "name": "Martin",
      "classification": "primary",
      "entity_type": "person",
      "primary": true,
      "person_id": "~{\"name\": \"Martin\"}",
      "organization_id": null
    },
    {
      "name": "Jeffries",
      "classification": "cosponsor",
      "entity_type": "person",
      "primary": false,
      "person_id": "~{\"name\": \"Jeffries\"}",
      "organization_id": null
    }
  ],
  "related_bills": [],
  "versions": [
    {
      "note": "Introduced Version",
      "links": [
        {
          "url": "https://www.wvlegislature.gov/Bill_Status/bills_text.cfm?billdoc=scr4%20intr.htm&yr=2025&sesstype=RS&i=4&houseorig=s&billtype=cr",
          "media_type": "text/html"
        }
      ],
      "date": "",
      "classification": ""
    }
  ],
  "documents": [],
  "citations": [],
  "sources": [
    {
      "url": "https://www.wvlegislature.gov/Bill_Status/Resolution_History.cfm?year=2025&sessiontype=RS&input4=4&billtype=cr&houseorig=s&btype=res",
      "note": ""
    }
  ],
  "extras": {},
  "jurisdiction": {
    "id": "ocd-jurisdiction/country:us/state:wv/government",
    "name": "West Virginia",
    "classification": "state",
    "division_id": "ocd-division/country:us/state:wv"
  },
  "_processing": {
    "logs_latest_update": "2025-10-25T03:51:36Z",
    "text_extraction_latest_update": "2025-10-28T10:30:05.065374Z"
  }
}